<?xml version="1.0" encoding="UTF-8"?>
<TrialsTrack>
    <Header>deadbeef</Header>
    <CompMethod>LZMA</CompMethod>
    <LzmaStripped>0</LzmaStripped>
    <PayloadType>OBJ5</PayloadType>
    <PreGlue>5452503115667f19bf2aff1c99a500234c0c54525033000000000000000000004c000000000000000000c30001860202490454525034002a00110010</PreGlue>
    <PostGlue>434d554c0118ffe7720119ffe772011dbf4242011ebf4242000045585430000054524732000042475231350f073e110d0d05020a0d0505050f0505050f0505050901050505050f011c02105041434b0000000154454e44</PostGlue>
    <Objects>
        <Obj t="0" v="45056" x="-56.382099" y="0.040007" z="8.009888" rx="0" ry="0" rz="0" s="127"/>
        <Obj t="52" v="46512" x="-39.162449" y="0.040005" z="8.201297" rx="0" ry="129" rz="0" s="0"/>
        <Obj t="176" v="181" x="-44.957584" y="1.374005" z="8.117311" rx="0" ry="0" rz="0" s="127"/>
        <Obj t="0" v="45056" x="-50.849751" y="1.373068" z="8.117311" rx="0" ry="0" rz="0" s="127"/>
        <Obj t="52" v="46512" x="-56.321171" y="1.373068" z="24.023804" rx="0" ry="0" rz="0" s="127"/>
        <Obj t="176" v="181" x="-56.321171" y="1.373068" z="19.806942" rx="0" ry="0" rz="0" s="127"/>
        <Obj t="0" v="45056" x="-48.333782" y="1.373068" z="19.806942" rx="0" ry="0" rz="0" s="127"/>
        <Obj t="42" v="46512" x="-56.321171" y="4.173892" z="19.806942" rx="0" ry="0" rz="0" s="127"/>
        <Obj t="176" v="181" x="-48.333782" y="4.173892" z="19.806942" rx="0" ry="0" rz="0" s="127"/>
        <Obj t="0" v="45056" x="-48.172611" y="1.373068" z="24.023804" rx="0" ry="0" rz="0" s="127"/>
        <Obj t="42" v="46512" x="-40.438118" y="1.373068" z="24.023804" rx="0" ry="0" rz="0" s="127"/>
        <Obj t="176" v="181" x="-40.438118" y="4.203189" z="24.023804" rx="0" ry="0" rz="0" s="127"/>
        <Obj t="0" v="45056" x="-48.172611" y="4.162173" z="24.023804" rx="0" ry="0" rz="0" s="127"/>
        <Obj t="42" v="46512" x="-56.321171" y="4.150454" z="24.023804" rx="0" ry="0" rz="0" s="127"/>
        <Obj t="176" v="181" x="-56.336796" y="1.039078" z="23.967163" rx="0" ry="0" rz="0" s="127"/>
        <Obj t="0" v="45056" x="-56.336796" y="1.039078" z="19.820616" rx="0" ry="0" rz="0" s="127"/>
        <Obj t="42" v="46512" x="-48.349407" y="1.039078" z="19.820616" rx="0" ry="0" rz="0" s="127"/>
        <Obj t="176" v="181" x="-56.336796" y="3.884825" z="19.820616" rx="0" ry="0" rz="0" s="127"/>
        <Obj t="0" v="45056" x="-48.349407" y="3.884825" z="19.820616" rx="0" ry="0" rz="0" s="127"/>
        <Obj t="42" v="46512" x="-48.219486" y="1.039078" z="23.967163" rx="0" ry="0" rz="0" s="127"/>
        <Obj t="176" v="181" x="-40.461555" y="1.039078" z="23.967163" rx="0" ry="0" rz="0" s="127"/>
        <Obj t="0" v="45056" x="-40.461555" y="3.888731" z="23.967163" rx="0" ry="0" rz="0" s="127"/>
        <Obj t="42" v="46512" x="-48.219486" y="3.892637" z="23.967163" rx="0" ry="0" rz="0" s="127"/>
        <Obj t="176" v="181" x="-56.336796" y="3.841856" z="23.967163" rx="0" ry="0" rz="0" s="127"/>
        <Obj t="0" v="45056" x="-57.454002" y="1.738308" z="23.939819" rx="0" ry="165" rz="0" s="89"/>
        <Obj t="42" v="46512" x="-56.336796" y="1.738308" z="23.939819" rx="0" ry="165" rz="0" s="89"/>
        <Obj t="176" v="181" x="-55.125839" y="1.738308" z="23.937866" rx="0" ry="165" rz="0" s="89"/>
        <Obj t="0" v="45056" x="-55.727413" y="2.689494" z="23.937866" rx="0" ry="165" rz="0" s="89"/>
        <Obj t="42" v="46512" x="-57.047745" y="2.689494" z="23.937866" rx="0" ry="165" rz="0" s="89"/>
        <Obj t="176" v="181" x="-57.047745" y="4.550851" z="23.937866" rx="0" ry="165" rz="0" s="89"/>
        <Obj t="0" v="45056" x="-55.993042" y="4.550851" z="23.937866" rx="0" ry="165" rz="0" s="89"/>
        <Obj t="42" v="46512" x="-54.914902" y="4.550851" z="23.937866" rx="0" ry="165" rz="0" s="89"/>
        <Obj t="176" v="181" x="-55.563347" y="5.523522" z="23.937866" rx="0" ry="165" rz="0" s="89"/>
        <Obj t="0" v="45056" x="-60.477486" y="0.640635" z="24.933973" rx="0" ry="165" rz="0" s="89"/>
        <Obj t="42" v="46512" x="-60.633739" y="0.640635" z="18.646769" rx="0" ry="165" rz="0" s="89"/>
        <Obj t="176" v="181" x="-37.234943" y="0.640635" z="22.168306" rx="0" ry="165" rz="0" s="89"/>
        <Obj t="0" v="45056" x="-33.953644" y="0.640635" z="18.773724" rx="0" ry="129" rz="0" s="0"/>
        <Obj t="42" v="46512" x="-44.654366" y="3.503064" z="6.749488" rx="0" ry="129" rz="0" s="0"/>
        <Obj t="176" v="181" x="-57.375877" y="0.613291" z="15.720943" rx="0" ry="129" rz="0" s="0"/>
        <Obj t="0" v="45056" x="-51.336720" y="0.613291" z="15.734615" rx="0" ry="129" rz="0" s="0"/>
        <Obj t="42" v="46512" x="-46.891342" y="1.796902" z="24.031616" rx="0" ry="0" rz="0" s="127"/>
        <Obj t="176" v="181" x="-47.664791" y="1.796902" z="24.412481" rx="0" ry="0" rz="0" s="127"/>
        <Obj t="0" v="45056" x="-47.953857" y="1.796902" z="23.474968" rx="0" ry="0" rz="0" s="127"/>
        <Obj t="44" v="46512" x="-48.719494" y="1.796902" z="23.973022" rx="0" ry="0" rz="0" s="127"/>
        <Obj t="176" v="181" x="-50.961716" y="0.607431" z="23.785519" rx="0" ry="11" rz="0" s="127"/>
        <Obj t="0" v="45056" x="-51.922668" y="0.607431" z="23.947632" rx="0" ry="11" rz="0" s="127"/>
        <Obj t="44" v="46512" x="-51.188282" y="0.607431" z="24.543343" rx="0" ry="11" rz="0" s="127"/>
        <Obj t="176" v="181" x="-45.367878" y="0.429694" z="23.187855" rx="168" ry="233" rz="18" s="87"/>
        <Obj t="0" v="45056" x="-44.430367" y="0.429694" z="22.984726" rx="168" ry="233" rz="18" s="87"/>
        <Obj t="44" v="47280" x="-47.000717" y="0.429694" z="23.840208" rx="168" ry="233" rz="18" s="87"/>
        <Obj t="176" v="184" x="-47.828854" y="0.429694" z="24.312870" rx="168" ry="233" rz="18" s="87"/>
        <Obj t="0" v="45056" x="-48.774181" y="0.429694" z="22.484718" rx="220" ry="167" rz="82" s="241"/>
        <Obj t="44" v="47280" x="-49.727322" y="1.796902" z="24.008179" rx="0" ry="0" rz="0" s="127"/>
        <Obj t="176" v="184" x="-48.227299" y="2.972702" z="24.008179" rx="0" ry="0" rz="0" s="127"/>
        <Obj t="0" v="45056" x="-47.149158" y="2.937545" z="24.242558" rx="0" ry="0" rz="0" s="127"/>
        <Obj t="44" v="47280" x="-47.047592" y="4.695384" z="24.244511" rx="0" ry="0" rz="0" s="127"/>
        <Obj t="176" v="184" x="-47.727291" y="4.695384" z="23.363638" rx="0" ry="0" rz="0" s="127"/>
        <Obj t="0" v="45056" x="-48.313236" y="4.695384" z="24.027710" rx="0" ry="0" rz="0" s="127"/>
        <Obj t="44" v="47024" x="-49.282001" y="4.695384" z="24.027710" rx="0" ry="0" rz="0" s="127"/>
        <Obj t="176" v="183" x="-48.883560" y="5.882902" z="24.027710" rx="0" ry="0" rz="0" s="127"/>
        <Obj t="0" v="45056" x="-47.688229" y="5.882902" z="24.027710" rx="0" ry="0" rz="0" s="127"/>
        <Obj t="44" v="47024" x="-41.367817" y="1.464866" z="24.150759" rx="0" ry="0" rz="0" s="127"/>
        <Obj t="176" v="183" x="-40.524055" y="1.464866" z="23.326529" rx="0" ry="0" rz="0" s="127"/>
        <Obj t="0" v="45056" x="-39.461540" y="1.464866" z="23.820677" rx="0" ry="0" rz="0" s="127"/>
        <Obj t="44" v="47024" x="-39.414665" y="1.919951" z="23.820677" rx="0" ry="0" rz="0" s="127"/>
        <Obj t="176" v="183" x="-40.899063" y="1.919951" z="23.605829" rx="0" ry="0" rz="0" s="127"/>
        <Obj t="0" v="45056" x="-41.414696" y="0.271489" z="22.211277" rx="1" ry="249" rz="0" s="127"/>
        <Obj t="44" v="9648" x="-40.367802" y="0.244144" z="21.443687" rx="1" ry="249" rz="0" s="127"/>
        <Obj t="176" v="37" x="-40.985001" y="0.703136" z="21.896818" rx="1" ry="249" rz="0" s="127"/>
        <Obj t="0" v="45056" x="-41.016251" y="1.103532" z="21.445641" rx="1" ry="249" rz="0" s="127"/>
        <Obj t="44" v="9648" x="-43.086594" y="0.259770" z="23.717159" rx="0" ry="247" rz="2" s="127"/>
        <Obj t="176" v="37" x="-43.156910" y="0.259770" z="24.902723" rx="0" ry="247" rz="2" s="127"/>
        <Obj t="0" v="45056" x="-41.992828" y="0.259770" z="23.984741" rx="0" ry="247" rz="2" s="127"/>
        <Obj t="78" v="9648" x="-41.735012" y="0.632822" z="20.976883" rx="66" ry="241" rz="189" s="84"/>
        <Obj t="176" v="37" x="-39.672482" y="0.501961" z="20.836256" rx="21" ry="4" rz="32" s="121"/>
        <Obj t="0" v="45056" x="-40.180302" y="2.347692" z="23.810909" rx="0" ry="0" rz="0" s="127"/>
        <Obj t="78" v="9648" x="-39.344349" y="4.285222" z="24.033569" rx="0" ry="0" rz="0" s="127"/>
        <Obj t="176" v="37" x="-40.352177" y="4.285222" z="24.613657" rx="0" ry="0" rz="0" s="127"/>
        <Obj t="0" v="45056" x="-40.500618" y="4.285222" z="23.568720" rx="0" ry="0" rz="0" s="127"/>
        <Obj t="78" v="9648" x="-41.578758" y="4.285222" z="24.115602" rx="0" ry="0" rz="0" s="127"/>
        <Obj t="176" v="37" x="-41.008438" y="4.775464" z="24.115602" rx="0" ry="0" rz="0" s="127"/>
        <Obj t="0" v="45056" x="-39.711544" y="4.781323" z="24.111696" rx="1" ry="0" rz="255" s="127"/>
        <Obj t="78" v="9648" x="-40.211552" y="5.281331" z="24.103884" rx="0" ry="1" rz="0" s="127"/>
        <Obj t="176" v="37" x="-40.219364" y="5.775479" z="24.103884" rx="0" ry="1" rz="0" s="127"/>
        <Obj t="0" v="45056" x="-66.454140" y="8.734509" z="23.348013" rx="0" ry="1" rz="0" s="127"/>
        <Obj t="78" v="9648" x="-66.074928" y="8.734509" z="19.042145" rx="0" ry="1" rz="0" s="127"/>
        <Obj t="176" v="37" x="-63.243153" y="8.728649" z="23.408560" rx="0" ry="1" rz="0" s="127"/>
        <Obj t="0" v="45056" x="-62.863976" y="8.728649" z="19.102692" rx="0" ry="1" rz="0" s="127"/>
        <Obj t="78" v="9648" x="-59.985291" y="8.728649" z="23.437859" rx="0" ry="1" rz="0" s="127"/>
        <Obj t="176" v="37" x="-59.606113" y="8.728649" z="19.131990" rx="0" ry="1" rz="0" s="127"/>
        <Obj t="0" v="45056" x="-63.493156" y="12.007996" z="23.453484" rx="0" ry="0" rz="167" s="91"/>
        <Obj t="78" v="9648" x="-59.954041" y="12.007996" z="23.453484" rx="0" ry="0" rz="167" s="91"/>
        <Obj t="176" v="37" x="-63.336903" y="14.699443" z="25.820707" rx="194" ry="63" rz="192" s="65"/>
        <Obj t="0" v="45056" x="-59.821224" y="14.699443" z="25.889067" rx="194" ry="63" rz="192" s="65"/>
        <Obj t="78" v="9648" x="-56.625862" y="14.711162" z="25.814848" rx="194" ry="63" rz="192" s="65"/>
        <Obj t="176" v="37" x="-56.696178" y="12.007996" z="23.453484" rx="0" ry="0" rz="167" s="91"/>
        <Obj t="0" v="45056" x="-56.688366" y="8.728649" z="23.455437" rx="0" ry="1" rz="0" s="127"/>
        <Obj t="78" v="9648" x="-56.309189" y="8.728649" z="19.149569" rx="0" ry="1" rz="0" s="127"/>
        <Obj t="176" v="175" x="-53.375816" y="8.722790" z="23.478874" rx="0" ry="1" rz="0" s="127"/>
        <Obj t="0" v="45056" x="-52.996639" y="8.722790" z="19.173006" rx="0" ry="1" rz="0" s="127"/>
        <Obj t="198" v="44976" x="-50.102325" y="8.722790" z="23.478874" rx="0" ry="1" rz="0" s="127"/>
        <Obj t="176" v="175" x="-49.723148" y="8.722790" z="19.173006" rx="0" ry="1" rz="0" s="127"/>
        <Obj t="0" v="45056" x="-51.016403" y="11.306813" z="23.320669" rx="0" ry="0" rz="0" s="127"/>
        <Obj t="198" v="44976" x="-47.703854" y="11.306813" z="23.277699" rx="0" ry="0" rz="0" s="127"/>
        <Obj t="176" v="175" x="-44.438179" y="11.306813" z="23.277699" rx="0" ry="0" rz="0" s="127"/>
        <Obj t="0" v="45056" x="-41.125626" y="11.306813" z="23.277699" rx="0" ry="0" rz="0" s="127"/>
        <Obj t="198" v="44976" x="-37.797451" y="11.306813" z="23.310902" rx="0" ry="0" rz="0" s="127"/>
        <Obj t="176" v="175" x="-34.609901" y="11.306813" z="23.310902" rx="0" ry="0" rz="0" s="127"/>
        <Obj t="0" v="45056" x="-31.898924" y="11.422050" z="25.779690" rx="0" ry="89" rz="0" s="91"/>
        <Obj t="198" v="44976" x="-46.789776" y="8.722790" z="23.502312" rx="0" ry="1" rz="0" s="127"/>
        <Obj t="176" v="198" x="-46.410599" y="8.722790" z="19.196444" rx="0" ry="1" rz="0" s="127"/>
        <Obj t="0" v="45056" x="-43.570976" y="8.722790" z="23.543327" rx="0" ry="1" rz="0" s="127"/>
        <Obj t="198" v="50864" x="-43.191799" y="8.722790" z="19.237459" rx="0" ry="1" rz="0" s="127"/>
        <Obj t="176" v="198" x="-40.289677" y="8.722790" z="23.572626" rx="0" ry="1" rz="0" s="127"/>
        <Obj t="0" v="45056" x="-39.910500" y="8.722790" z="19.266758" rx="0" ry="1" rz="0" s="127"/>
        <Obj t="198" v="50864" x="-37.000565" y="8.722790" z="23.603876" rx="0" ry="1" rz="0" s="127"/>
        <Obj t="176" v="198" x="-36.621387" y="8.722790" z="19.298008" rx="0" ry="1" rz="0" s="127"/>
        <Obj t="0" v="45056" x="-33.766140" y="8.722790" z="23.662470" rx="0" ry="1" rz="0" s="127"/>
        <Obj t="198" v="50864" x="-33.386963" y="8.722790" z="19.356602" rx="0" ry="1" rz="0" s="127"/>
        <Obj t="176" v="198" x="-33.758327" y="5.500084" z="23.402700" rx="255" ry="1" rz="89" s="90"/>
        <Obj t="0" v="45056" x="-35.930237" y="5.500084" z="23.402700" rx="255" ry="1" rz="89" s="90"/>
        <Obj t="25" v="50864" x="-35.852108" y="2.894575" z="25.875395" rx="60" ry="63" rz="66" s="65"/>
        <Obj t="176" v="198" x="-33.734890" y="2.218784" z="23.402700" rx="255" ry="1" rz="89" s="90"/>
        <Obj t="0" v="45056" x="-33.727077" y="-1.003922" z="23.355825" rx="255" ry="1" rz="89" s="90"/>
        <Obj t="25" v="50864" x="-33.688015" y="-4.252018" z="23.375357" rx="255" ry="1" rz="89" s="90"/>
        <Obj t="176" v="198" x="-30.477028" y="8.722790" z="23.713253" rx="0" ry="1" rz="0" s="127"/>
        <Obj t="0" v="45056" x="-30.097834" y="8.722790" z="19.407385" rx="0" ry="1" rz="0" s="127"/>
        <Obj t="25" v="50864" x="-28.320745" y="8.722790" z="23.728878" rx="0" ry="1" rz="0" s="127"/>
        <Obj t="176" v="198" x="-63.516594" y="9.642725" z="23.445671" rx="4" ry="90" rz="166" s="252"/>
        <Obj t="0" v="45056" x="-60.008728" y="9.642725" z="23.445671" rx="4" ry="90" rz="166" s="252"/>
        <Obj t="25" v="50864" x="-56.743053" y="9.642725" z="23.445671" rx="4" ry="90" rz="166" s="252"/>
        <Obj t="176" v="198" x="-53.477379" y="9.642725" z="23.445671" rx="4" ry="90" rz="166" s="252"/>
        <Obj t="0" v="45056" x="-33.742702" y="7.888792" z="23.547234" rx="170" ry="0" rz="0" s="163"/>
        <Obj t="25" v="11696" x="-35.930237" y="7.890745" z="23.459343" rx="170" ry="0" rz="0" s="163"/>
        <Obj t="176" v="45" x="-56.657116" y="14.340062" z="23.660517" rx="62" ry="65" rz="61" s="190"/>
        <Obj t="0" v="45056" x="-53.172688" y="11.099779" z="23.449577" rx="93" ry="85" rz="246" s="9"/>
        <Obj t="25" v="11696" x="-35.883362" y="3.216846" z="23.613642" rx="58" ry="199" rz="188" s="186"/>
        <Obj t="176" v="45" x="-32.297367" y="11.345877" z="23.529655" rx="86" ry="0" rz="0" s="162"/>
        <Obj t="0" v="45056" x="-59.899353" y="14.340062" z="23.683954" rx="62" ry="65" rz="61" s="190"/>
        <Obj t="25" v="10928" x="-63.407219" y="14.340062" z="23.654657" rx="62" ry="65" rz="61" s="190"/>
        <Obj t="176" v="42" x="-57.375877" y="1.281270" z="19.822569" rx="0" ry="161" rz="0" s="84"/>
        <Obj t="0" v="45056" x="-56.696178" y="1.281270" z="19.822569" rx="0" ry="165" rz="0" s="88"/>
        <Obj t="25" v="10928" x="-56.157108" y="1.281270" z="19.822569" rx="0" ry="165" rz="0" s="88"/>
        <Obj t="176" v="42" x="-55.821163" y="1.281270" z="19.822569" rx="0" ry="168" rz="0" s="92"/>
        <Obj t="0" v="45056" x="-55.399284" y="1.281270" z="19.822569" rx="0" ry="168" rz="0" s="92"/>
        <Obj t="25" v="10928" x="-55.547722" y="1.601587" z="19.822569" rx="0" ry="165" rz="0" s="89"/>
        <Obj t="176" v="42" x="-56.063354" y="1.601587" z="19.822569" rx="0" ry="165" rz="0" s="89"/>
        <Obj t="0" v="45056" x="-56.836803" y="1.601587" z="19.822569" rx="0" ry="165" rz="0" s="89"/>
        <Obj t="25" v="49584" x="-57.336811" y="1.601587" z="19.822569" rx="0" ry="163" rz="0" s="87"/>
        <Obj t="176" v="193" x="-56.875870" y="4.117250" z="19.594049" rx="0" ry="163" rz="0" s="87"/>
        <Obj t="0" v="45056" x="-56.141483" y="4.117250" z="19.594049" rx="0" ry="172" rz="0" s="95"/>
        <Obj t="25" v="49584" x="-55.672726" y="4.117250" z="19.594049" rx="0" ry="172" rz="0" s="95"/>
        <Obj t="176" v="193" x="-55.164906" y="4.117250" z="19.594049" rx="0" ry="171" rz="0" s="94"/>
        <Obj t="0" v="45056" x="-55.164906" y="4.437568" z="19.594049" rx="0" ry="171" rz="0" s="94"/>
        <Obj t="25" v="7344" x="-55.664913" y="4.437568" z="19.594049" rx="0" ry="171" rz="0" s="94"/>
        <Obj t="176" v="28" x="-56.110229" y="4.437568" z="19.594049" rx="0" ry="171" rz="0" s="94"/>
        <Obj t="0" v="45056" x="-57.047745" y="4.437568" z="19.594049" rx="0" ry="189" rz="0" s="108"/>
        <Obj t="25" v="33456" x="-56.563362" y="4.709056" z="19.603815" rx="0" ry="168" rz="0" s="92"/>
        <Obj t="176" v="130" x="-56.063354" y="4.709056" z="19.603815" rx="0" ry="168" rz="0" s="92"/>
        <Obj t="0" v="45056" x="-55.649288" y="4.709056" z="19.603815" rx="0" ry="168" rz="0" s="92"/>
        <Obj t="25" v="41136" x="-55.211781" y="4.709056" z="19.603815" rx="0" ry="168" rz="0" s="92"/>
        <Obj t="176" v="159" x="-25.828520" y="9.974762" z="-7.140734" rx="0" ry="0" rz="0" s="127"/>
        <Obj t="0" v="45056" x="-31.797359" y="9.974762" z="-7.175891" rx="0" ry="0" rz="0" s="127"/>
        <Obj t="25" v="37552" x="-37.805264" y="9.974762" z="-7.213001" rx="0" ry="0" rz="0" s="127"/>
        <Obj t="176" v="131" x="-43.774105" y="9.974762" z="-7.205188" rx="0" ry="0" rz="0" s="127"/>
        <Obj t="0" v="45056" x="-49.758572" y="9.974762" z="-7.218860" rx="0" ry="0" rz="0" s="127"/>
        <Obj t="25" v="33712" x="-55.758663" y="9.974762" z="-7.236439" rx="0" ry="0" rz="0" s="127"/>
        <Obj t="176" v="131" x="-61.743130" y="9.974762" z="-7.214954" rx="0" ry="0" rz="0" s="127"/>
        <Obj t="0" v="45056" x="-67.719780" y="9.974762" z="-7.255970" rx="0" ry="0" rz="0" s="127"/>
        <Obj t="25" v="13488" x="-31.859861" y="10.697429" z="-5.847745" rx="0" ry="0" rz="0" s="127"/>
        <Obj t="176" v="52" x="-25.828520" y="10.697429" z="-5.814542" rx="0" ry="0" rz="0" s="127"/>
        <Obj t="0" v="45056" x="-37.852139" y="10.629068" z="-5.834074" rx="0" ry="0" rz="0" s="127"/>
        <Obj t="25" v="13488" x="-43.805355" y="10.629068" z="-5.861418" rx="0" ry="0" rz="0" s="127"/>
        <Obj t="176" v="52" x="-49.758572" y="10.629068" z="-5.859465" rx="0" ry="0" rz="0" s="127"/>
        <Obj t="0" v="45056" x="-55.750851" y="10.629068" z="-5.898528" rx="0" ry="0" rz="0" s="127"/>
        <Obj t="25" v="13488" x="-67.758850" y="10.629068" z="-5.929778" rx="0" ry="0" rz="0" s="127"/>
        <Obj t="176" v="52" x="-67.727592" y="10.629068" z="-8.537240" rx="0" ry="0" rz="0" s="127"/>
        <Obj t="0" v="45056" x="-61.743130" y="10.629068" z="-8.502083" rx="0" ry="0" rz="0" s="127"/>
        <Obj t="25" v="16816" x="-55.719601" y="10.629068" z="-8.525520" rx="0" ry="0" rz="0" s="127"/>
        <Obj t="176" v="65" x="-49.758572" y="10.629068" z="-8.537240" rx="0" ry="0" rz="0" s="127"/>
        <Obj t="0" v="45056" x="-43.750668" y="10.629068" z="-8.478645" rx="0" ry="0" rz="0" s="127"/>
        <Obj t="25" v="16816" x="-37.805264" y="10.629068" z="-8.525520" rx="0" ry="0" rz="0" s="127"/>
        <Obj t="176" v="65" x="-31.797359" y="10.629068" z="-8.472786" rx="0" ry="0" rz="0" s="127"/>
        <Obj t="0" v="45056" x="-25.812893" y="10.629068" z="-8.457160" rx="0" ry="0" rz="0" s="127"/>
        <Obj t="33" v="16816" x="-62.383766" y="8.664195" z="-4.136782" rx="0" ry="91" rz="0" s="89"/>
        <Obj t="176" v="65" x="-62.399391" y="5.894621" z="-0.851575" rx="0" ry="91" rz="0" s="89"/>
        <Obj t="0" v="45056" x="-62.438454" y="3.111376" z="2.560586" rx="0" ry="91" rz="0" s="89"/>
        <Obj t="33" v="16816" x="-62.446266" y="0.306645" z="5.851652" rx="0" ry="91" rz="0" s="89"/>
        <Obj t="176" v="65" x="-62.540016" y="1.183612" z="2.164095" rx="0" ry="167" rz="0" s="90"/>
        <Obj t="0" v="45056" x="-62.336887" y="1.183612" z="-3.041062" rx="0" ry="167" rz="0" s="90"/>
        <Obj t="33" v="14256" x="-62.336887" y="4.005920" z="-3.041062" rx="0" ry="167" rz="0" s="90"/>
        <Obj t="176" v="55" x="-62.336887" y="6.849714" z="-3.041062" rx="0" ry="167" rz="0" s="90"/>
        <Obj t="0" v="45056" x="-62.336887" y="9.586083" z="-3.041062" rx="0" ry="167" rz="0" s="90"/>
        <Obj t="33" v="14256" x="-62.540016" y="3.767636" z="2.164095" rx="0" ry="167" rz="0" s="90"/>
        <Obj t="176" v="55" x="-59.993103" y="10.935714" z="22.988632" rx="0" ry="252" rz="0" s="127"/>
        <Obj t="0" v="45056" x="-59.993103" y="9.857573" z="22.988632" rx="0" ry="252" rz="0" s="127"/>
        <Obj t="33" v="14256" x="-56.743053" y="9.857573" z="23.066759" rx="0" ry="252" rz="0" s="127"/>
        <Obj t="176" v="152" x="-53.485191" y="9.857573" z="23.051132" rx="0" ry="252" rz="0" s="127"/>
        <Obj t="0" v="45056" x="-29.234821" y="1.300801" z="18.252232" rx="0" ry="166" rz="0" s="90"/>
        <Obj t="33" v="39088" x="-29.172319" y="1.279316" z="15.980713" rx="0" ry="166" rz="0" s="90"/>
        <Obj t="176" v="152" x="-34.180210" y="-0.779309" z="21.555016" rx="0" ry="90" rz="0" s="166"/>
        <Obj t="0" v="45056" x="-35.516167" y="-0.779309" z="23.181993" rx="0" ry="90" rz="0" s="166"/>
        <Obj t="33" v="39088" x="-67.797913" y="3.025437" z="16.093996" rx="0" ry="164" rz="0" s="168"/>
        <Obj t="176" v="152" x="-67.860413" y="3.013718" z="24.049194" rx="0" ry="164" rz="0" s="168"/>
        <Obj t="0" v="45056" x="-67.562439" y="2.964881" z="8.018447" rx="0" ry="92" rz="0" s="88"/>
        <Obj t="33" v="39088" x="-52.563301" y="11.816586" z="22.978867" rx="0" ry="164" rz="0" s="168"/>
        <Obj t="176" v="42" x="-48.555428" y="8.955215" z="23.193714" rx="0" ry="164" rz="0" s="168"/>
        <Obj t="0" v="45056" x="-42.031891" y="8.963027" z="23.369497" rx="0" ry="164" rz="0" s="168"/>
        <Obj t="33" v="10928" x="-29.812954" y="0.025391" z="9.798978" rx="1" ry="164" rz="1" s="168"/>
        <Obj t="176" v="42" x="-29.766079" y="0.003906" z="3.552788" rx="255" ry="92" rz="0" s="88"/>
        <Obj t="0" v="45056" x="-33.138596" y="0.040002" z="3.239960" rx="255" ry="92" rz="0" s="88"/>
        <Obj t="33" v="10928" x="-29.836393" y="0.003906" z="-2.251987" rx="255" ry="92" rz="0" s="88"/>
        <Obj t="176" v="197" x="-32.971645" y="0.040002" z="-2.490202" rx="255" ry="92" rz="0" s="88"/>
        <Obj t="0" v="45056" x="-35.812843" y="0.040002" z="-2.508976" rx="255" ry="82" rz="0" s="97"/>
        <Obj t="33" v="50608" x="-29.797329" y="1.111345" z="10.060700" rx="22" ry="87" rz="235" s="87"/>
        <Obj t="176" v="197" x="-29.844206" y="0.820325" z="9.158343" rx="20" ry="88" rz="236" s="87"/>
        <Obj t="0" v="45056" x="-29.891081" y="0.603525" z="8.306767" rx="18" ry="88" rz="238" s="88"/>
        <Obj t="33" v="50608" x="-29.906706" y="0.583993" z="7.976684" rx="18" ry="88" rz="238" s="88"/>
        <Obj t="176" v="197" x="-29.797329" y="1.459007" z="9.959136" rx="14" ry="89" rz="242" s="89"/>
        <Obj t="0" v="45056" x="-29.937958" y="1.091814" z="8.527473" rx="23" ry="87" rz="233" s="87"/>
        <Obj t="33" v="50608" x="-29.992645" y="0.716808" z="7.615351" rx="22" ry="87" rz="234" s="87"/>
        <Obj t="176" v="197" x="-30.070772" y="0.765637" z="7.498161" rx="22" ry="89" rz="233" s="85"/>
        <Obj t="0" v="45056" x="-32.875504" y="0.046876" z="-9.611475" rx="3" ry="1" rz="0" s="129"/>
        <Obj t="33" v="5008" x="-33.508324" y="0.046876" z="-6.709087" rx="3" ry="1" rz="0" s="129"/>
        <Obj t="176" v="44" x="-40.266239" y="0.046876" z="-9.875151" rx="0" ry="127" rz="3" s="0"/>
        <Obj t="0" v="45056" x="-41.805325" y="0.046876" z="-8.214969" rx="0" ry="127" rz="3" s="0"/>
        <Obj t="33" v="11440" x="-42.141270" y="0.039063" z="-6.287205" rx="0" ry="127" rz="3" s="0"/>
        <Obj t="176" v="44" x="-38.867779" y="0.455085" z="-8.777477" rx="241" ry="131" rz="253" s="19"/>
        <Obj t="0" v="45056" x="-38.961533" y="0.662120" z="-8.804822" rx="241" ry="131" rz="253" s="19"/>
        <Obj t="33" v="11440" x="-40.297489" y="1.375021" z="-9.062638" rx="233" ry="132" rz="252" s="17"/>
        <Obj t="176" v="126" x="-40.609993" y="0.603525" z="-7.701289" rx="238" ry="133" rz="7" s="25"/>
        <Obj t="0" v="45056" x="-41.180317" y="0.945327" z="-6.855573" rx="241" ry="135" rz="1" s="35"/>
        <Obj t="33" v="32432" x="-39.555290" y="0.667979" z="-6.117281" rx="233" ry="136" rz="255" s="35"/>
        <Obj t="176" v="126" x="-55.383659" y="1.371115" z="-8.418097" rx="0" ry="129" rz="0" s="255"/>
        <Obj t="0" v="45056" x="-55.383659" y="4.177798" z="-8.418097" rx="0" ry="129" rz="0" s="255"/>
        <Obj t="33" v="32432" x="-49.039810" y="1.371115" z="-8.472786" rx="0" ry="129" rz="0" s="3"/>
        <Obj t="176" v="126" x="-49.039810" y="4.211002" z="-8.472786" rx="0" ry="129" rz="0" s="3"/>
        <Obj t="0" v="45056" x="-47.938232" y="0.662120" z="-3.988342" rx="0" ry="255" rz="0" s="127"/>
        <Obj t="33" v="32432" x="-51.094528" y="0.662120" z="-3.882872" rx="0" ry="255" rz="0" s="127"/>
        <Obj t="176" v="126" x="-57.516502" y="0.662120" z="-4.002014" rx="0" ry="255" rz="0" s="127"/>
        <Obj t="0" v="45056" x="-58.922775" y="0.662120" z="-6.025483" rx="0" ry="166" rz="0" s="90"/>
        <Obj t="33" v="32432" x="-58.907150" y="0.662120" z="-9.320455" rx="0" ry="166" rz="0" s="90"/>
        <Obj t="176" v="126" x="-46.172581" y="0.705089" z="-5.490318" rx="0" ry="90" rz="0" s="90"/>
        <Obj t="0" v="45056" x="-46.102264" y="0.705089" z="-9.004044" rx="0" ry="90" rz="0" s="90"/>
        <Obj t="33" v="32432" x="-48.156986" y="3.899756" z="7.000107" rx="0" ry="0" rz="0" s="127"/>
        <Obj t="176" v="126" x="-55.399284" y="1.054704" z="-8.406378" rx="0" ry="0" rz="0" s="127"/>
        <Obj t="0" v="45056" x="-55.399284" y="3.824277" z="-8.406378" rx="0" ry="0" rz="0" s="127"/>
        <Obj t="33" v="36016" x="-49.157001" y="1.037125" z="-8.517708" rx="0" ry="0" rz="0" s="127"/>
        <Obj t="176" v="140" x="-49.157001" y="3.857481" z="-8.517708" rx="0" ry="0" rz="0" s="127"/>
        <Obj t="0" v="45056" x="-54.438332" y="4.255924" z="-8.929824" rx="166" ry="0" rz="0" s="90"/>
        <Obj t="33" v="44928" x="-55.321156" y="4.255924" z="-8.941543" rx="166" ry="249" rz="7" s="89"/>
        <Obj t="176" v="175" x="-56.274296" y="4.255924" z="-7.705196" rx="19" ry="87" rz="168" s="237"/>
        <Obj t="0" v="32768" x="-56.407112" y="1.484398" z="-7.705196" rx="16" ry="168" rz="89" s="241"/>
        <Obj t="181" v="50304" x="-55.727413" y="1.486351" z="-7.691524" rx="15" ry="88" rz="167" s="242"/>
        <Obj t="176" v="45" x="-54.680523" y="1.486351" z="-7.675899" rx="10" ry="167" rz="89" s="246"/>
        <Obj t="0" v="32768" x="-54.086761" y="1.484398" z="-7.660273" rx="7" ry="167" rz="90" s="249"/>
        <Obj t="181" v="7808" x="-54.360203" y="1.970733" z="-7.724727" rx="248" ry="82" rz="160" s="10"/>
        <Obj t="176" v="30" x="-56.071167" y="1.962921" z="-7.785275" rx="210" ry="60" rz="157" s="229"/>
        <Obj t="0" v="32768" x="-54.774273" y="4.580148" z="-7.546990" rx="49" ry="180" rz="81" s="39"/>
        <Obj t="181" v="7808" x="-55.047714" y="4.837965" z="-9.015762" rx="231" ry="193" rz="162" s="51"/>
        <Obj t="176" v="30" x="-48.477303" y="4.656321" z="-8.593882" rx="255" ry="1" rz="162" s="170"/>
        <Obj t="0" v="32768" x="-48.555428" y="1.818387" z="-8.515755" rx="255" ry="1" rz="162" s="170"/>
        <Obj t="181" v="7808" x="-50.737259" y="2.814220" z="8.000107" rx="0" ry="0" rz="0" s="127"/>
        <Obj t="176" v="30" x="-44.734161" y="2.817711" z="8.000092" rx="0" ry="0" rz="0" s="127"/>
        <Obj t="0" v="32768" x="-52.138557" y="3.561625" z="6.599532" rx="0" ry="0" rz="0" s="127"/>
        <Obj t="181" v="7808" x="-49.336475" y="1.531281" z="4.909625" rx="0" ry="166" rz="0" s="90"/>
        <Obj t="176" v="30" x="-48.545181" y="1.288160" z="19.787392" rx="7" ry="0" rz="255" s="129"/>
        <Obj t="0" v="32768" x="-48.172016" y="1.353675" z="19.783697" rx="5" ry="0" rz="0" s="129"/>
        <Obj t="181" v="7808" x="-48.684174" y="1.413695" z="19.784380" rx="5" ry="0" rz="0" s="129"/>
        <Obj t="176" v="110" x="-48.413097" y="1.481170" z="19.796429" rx="6" ry="0" rz="4" s="129"/>
        <Obj t="0" v="32768" x="-48.430141" y="1.541026" z="19.782772" rx="7" ry="254" rz="1" s="129"/>
        <Obj t="181" v="28288" x="-48.426975" y="4.165754" z="19.774303" rx="1" ry="254" rz="0" s="129"/>
        <Obj t="176" v="110" x="-48.283966" y="4.196020" z="19.776375" rx="3" ry="254" rz="1" s="129"/>
        <Obj t="0" v="32768" x="-48.569637" y="4.249515" z="19.778288" rx="5" ry="254" rz="252" s="129"/>
        <Obj t="181" v="28288" x="-48.007812" y="4.296347" z="19.777361" rx="4" ry="254" rz="0" s="129"/>
        <Obj t="176" v="107" x="-51.801426" y="3.216642" z="12.978476" rx="0" ry="0" rz="0" s="127"/>
        <Obj t="0" v="45056" x="-40.514843" y="3.216642" z="12.978476" rx="0" ry="0" rz="0" s="127"/>
        <Obj t="181" v="27568" x="-52.209648" y="3.216642" z="12.994561" rx="0" ry="0" rz="0" s="127"/>
        <Obj t="176" v="119" x="-40.923065" y="3.216642" z="12.994561" rx="0" ry="0" rz="0" s="127"/>
        <Obj t="0" v="32768" x="-52.066628" y="7.096491" z="12.581926" rx="222" ry="0" rz="0" s="122"/>
        <Obj t="181" v="30592" x="-40.780045" y="7.096491" z="12.581926" rx="222" ry="0" rz="0" s="122"/>
        <Obj t="176" v="119" x="-28.669909" y="7.511302" z="8.182705" rx="0" ry="166" rz="0" s="90"/>
        <Obj t="0" v="32768" x="-28.206341" y="7.511302" z="-0.389089" rx="0" ry="166" rz="0" s="90"/>
        <Obj t="181" v="30592" x="-29.851433" y="7.511302" z="15.996458" rx="0" ry="166" rz="0" s="90"/>
        <Obj t="176" v="119" x="-55.943752" y="8.712450" z="-11.713266" rx="0" ry="129" rz="0" s="0"/>
        <Obj t="0" v="32768" x="-40.003555" y="8.748542" z="-11.959552" rx="0" ry="129" rz="0" s="0"/>
        <Obj t="181" v="5504" x="-32.998688" y="1.042751" z="7.000107" rx="0" ry="0" rz="0" s="127"/>
    </Objects>
    <Joints/>
</TrialsTrack>
